[
	{
		"__TYPE__": "SharedSliceContent",
		"variation": "default",
		"primary": {
			"title": {
				"__TYPE__": "StructuredTextContent",
				"value": [
					{
						"type": "paragraph",
						"content": {
							"text": "Ullamco dolor officia labore. Nisi amet voluptate sint veniam magna proident quis ex officia aliqua non sit reprehenderit fugiat velit. In aute sit mollit minim magna."
						}
					}
				]
			},
			"sub_title": {
				"__TYPE__": "StructuredTextContent",
				"value": [
					{
						"type": "paragraph",
						"content": {
							"text": "Nulla nulla reprehenderit velit esse occaecat officia dolor in qui voluptate dolore dolore. Laborum eiusmod esse dolore aliqua."
						}
					}
				]
			},
			"menu": {
				"__TYPE__": "StructuredTextContent",
				"value": [
					{
						"type": "paragraph",
						"content": {
							"text": "Qui anim proident Lorem aliquip exercitation culpa aliquip minim sunt cillum et voluptate sunt dolore tempor."
						}
					}
				]
			},
			"button_link": {
				"__TYPE__": "LinkContent",
				"value": {
					"__TYPE__": "ExternalLink",
					"url": "http://twitter.com"
				}
			},
			"hero_image": {
				"origin": {
					"id": "main",
					"url": "https://images.unsplash.com/photo-1600861194802-a2b11076bc51",
					"width": 2545,
					"height": 2545
				},
				"url": "https://images.unsplash.com/photo-1600861194802-a2b11076bc51",
				"width": 2545,
				"height": 2545,
				"edit": {
					"zoom": 1,
					"crop": {
						"x": 0,
						"y": 0
					},
					"background": "transparent"
				},
				"credits": null,
				"alt": null,
				"__TYPE__": "ImageContent",
				"thumbnails": {}
			}
		},
		"items": []
	},
	{
		"__TYPE__": "SharedSliceContent",
		"variation": "heroNoButtonSmallBanner",
		"primary": {
			"title": {
				"__TYPE__": "StructuredTextContent",
				"value": [
					{
						"type": "paragraph",
						"content": {
							"text": "Sunt ea consectetur veniam ullamco est labore. Veniam do magna non irure."
						}
					}
				]
			},
			"sub_title": {
				"__TYPE__": "StructuredTextContent",
				"value": [
					{
						"type": "paragraph",
						"content": {
							"text": "Deserunt eu eu excepteur duis officia magna voluptate labore."
						}
					}
				]
			},
			"menu": {
				"__TYPE__": "StructuredTextContent",
				"value": [
					{
						"type": "paragraph",
						"content": {
							"text": "Proident amet velit anim et est aliqua cillum elit."
						}
					}
				]
			},
			"button_link": {
				"__TYPE__": "LinkContent",
				"value": {
					"__TYPE__": "ExternalLink",
					"url": "https://slicemachine.dev"
				}
			},
			"hero_image": {
				"__TYPE__": "ImageContent",
				"origin": {
					"id": "main",
					"url": "https://images.unsplash.com/photo-1587613865763-4b8b0d19e8ab",
					"width": 12288,
					"height": 16384
				},
				"url": "https://images.unsplash.com/photo-1587613865763-4b8b0d19e8ab",
				"width": 12288,
				"height": 16384,
				"edit": {
					"zoom": 1,
					"crop": {
						"x": 0,
						"y": 0
					},
					"background": "transparent"
				},
				"thumbnails": {}
			}
		},
		"items": [
			{
				"__TYPE__": "GroupItemContent",
				"value": []
			}
		]
	}
]